[{"id":"2ff24d6.8deb4b2","type":"tab","label":"MeasTemp","disabled":false,"info":""},{"id":"1bcfd80.b998128","type":"inject","z":"2ff24d6.8deb4b2","name":"","topic":"","payload":"","payloadType":"date","repeat":"1","crontab":"","once":false,"onceDelay":0.1,"x":190,"y":160,"wires":[["2b38f690.27eeea","a460d71e.253268"]]},{"id":"2b38f690.27eeea","type":"exec","z":"2ff24d6.8deb4b2","command":"vcgencmd measure_temp","addpay":false,"append":"","useSpawn":"false","timer":"","oldrc":false,"name":"measGPU","x":390,"y":160,"wires":[["2b452349.0f458c"],[],[]]},{"id":"a460d71e.253268","type":"exec","z":"2ff24d6.8deb4b2","command":"cat /sys/class/thermal/thermal_zone0/temp","addpay":false,"append":"","useSpawn":"false","timer":"","oldrc":false,"name":"measCPU","x":390,"y":280,"wires":[["9f18e820.db9ee8"],[],[]]},{"id":"2b452349.0f458c","type":"function","z":"2ff24d6.8deb4b2","name":"GPU T.","func":"str = msg.payload\nmsg.payload = str.substring(5,9);\nreturn msg;","outputs":1,"noerr":0,"x":610,"y":160,"wires":[["f62e8a84.f00938"]]},{"id":"9f18e820.db9ee8","type":"function","z":"2ff24d6.8deb4b2","name":"CPU T.","func":"str = msg.payload\nmsg.payload = str.substring()/1000;\nreturn msg;","outputs":1,"noerr":0,"x":610,"y":280,"wires":[["83f687d5.fdad18"]]},{"id":"f62e8a84.f00938","type":"ui_gauge","z":"2ff24d6.8deb4b2","name":"GPU Temp","group":"d34ca692.4ce7c8","order":2,"width":0,"height":0,"gtype":"gage","title":"GPU Temp","label":"°C","format":"{{value}}","min":0,"max":"100","colors":["#00b500","#e6e600","#ca3838"],"seg1":"","seg2":"","x":820,"y":160,"wires":[]},{"id":"83f687d5.fdad18","type":"ui_gauge","z":"2ff24d6.8deb4b2","name":"CPU Temp","group":"d34ca692.4ce7c8","order":1,"width":0,"height":0,"gtype":"gage","title":"CPU Temp","label":"°C","format":"{{value}}","min":0,"max":"100","colors":["#00b500","#e6e600","#ca3838"],"seg1":"","seg2":"","x":820,"y":280,"wires":[]},{"id":"849095ae.bef2b8","type":"watch","z":"2ff24d6.8deb4b2","name":"Watch NewImg Folder","files":"/home/pi/Pictures/NewImg","recursive":"","x":200,"y":460,"wires":[["159e6c0f.486454","96c5b7fa.be6078"]]},{"id":"fcb1c29e.10e26","type":"comment","z":"2ff24d6.8deb4b2","name":"terminal command","info":"","x":390,"y":100,"wires":[]},{"id":"d3910d71.05135","type":"comment","z":"2ff24d6.8deb4b2","name":"Repeat Interval 1s","info":"","x":190,"y":100,"wires":[]},{"id":"aa556590.280b68","type":"image","z":"2ff24d6.8deb4b2","name":"","width":"480","x":780,"y":740,"wires":[]},{"id":"159e6c0f.486454","type":"file in","z":"2ff24d6.8deb4b2","name":"","filename":"","format":"","chunk":false,"sendError":false,"encoding":"none","x":480,"y":660,"wires":[["aa556590.280b68","7621c09c.e64b58"]]},{"id":"b01f9814.638a98","type":"debug","z":"2ff24d6.8deb4b2","name":"ssh error","active":true,"tosidebar":true,"console":false,"tostatus":false,"complete":"payload","targetType":"msg","x":760,"y":540,"wires":[]},{"id":"785d5b6d.67b244","type":"debug","z":"2ff24d6.8deb4b2","name":"stdout","active":true,"tosidebar":true,"console":false,"tostatus":false,"complete":"payload","targetType":"msg","x":750,"y":460,"wires":[]},{"id":"96c5b7fa.be6078","type":"exec","z":"2ff24d6.8deb4b2","command":"scp","addpay":true,"append":"pi@master:/home/pi/Desktop/TempImg","useSpawn":"false","timer":"","oldrc":false,"name":"","x":470,"y":480,"wires":[["785d5b6d.67b244"],[],["b01f9814.638a98"]]},{"id":"65861fd.de115e","type":"ui_template","z":"2ff24d6.8deb4b2","group":"d34ca692.4ce7c8","name":"","order":3,"width":0,"height":0,"format":"<img width=\"100%\" height=\"100%\" src=\"data:image/png;base64,{{msg.payload}}\" />","storeOutMessages":true,"fwdInMessages":true,"templateScope":"local","x":940,"y":660,"wires":[[]]},{"id":"fd178b64.2b4318","type":"comment","z":"2ff24d6.8deb4b2","name":"Detect changes in folder","info":"","x":210,"y":420,"wires":[]},{"id":"a71d37b2.fb0e38","type":"comment","z":"2ff24d6.8deb4b2","name":"terminal command (SSH)","info":"","x":510,"y":420,"wires":[]},{"id":"f7ad21f9.94cb5","type":"comment","z":"2ff24d6.8deb4b2","name":"terminal command","info":"","x":390,"y":220,"wires":[]},{"id":"b1de437a.9c364","type":"comment","z":"2ff24d6.8deb4b2","name":"format substring","info":"","x":620,"y":100,"wires":[]},{"id":"af3d0ec.a996bf","type":"comment","z":"2ff24d6.8deb4b2","name":"format substring","info":"","x":616,"y":220,"wires":[]},{"id":"5356db4b.253c14","type":"comment","z":"2ff24d6.8deb4b2","name":"output to dashboard","info":"","x":830,"y":100,"wires":[]},{"id":"8efbccf1.2b049","type":"comment","z":"2ff24d6.8deb4b2","name":"output to dashboard","info":"","x":830,"y":220,"wires":[]},{"id":"a6b1a899.07d778","type":"comment","z":"2ff24d6.8deb4b2","name":"display command","info":"","x":780,"y":420,"wires":[]},{"id":"f0104da4.2df458","type":"comment","z":"2ff24d6.8deb4b2","name":"display error msg","info":"","x":780,"y":500,"wires":[]},{"id":"31a06cb9.4a5054","type":"comment","z":"2ff24d6.8deb4b2","name":"convert to object buffer","info":"","x":520,"y":620,"wires":[]},{"id":"a937252c.cba198","type":"comment","z":"2ff24d6.8deb4b2","name":"output to UI","info":"","x":770,"y":620,"wires":[]},{"id":"41f27f85.e288c","type":"comment","z":"2ff24d6.8deb4b2","name":"preview image","info":"","x":770,"y":700,"wires":[]},{"id":"7621c09c.e64b58","type":"base64","z":"2ff24d6.8deb4b2","name":"","action":"str","property":"payload","x":760,"y":660,"wires":[["65861fd.de115e"]]},{"id":"d34ca692.4ce7c8","type":"ui_group","z":"","name":"Default","tab":"6d2dae4e.18c32","disp":true,"width":"6","collapse":false},{"id":"6d2dae4e.18c32","type":"ui_tab","z":"","name":"Home","icon":"dashboard","disabled":false,"hidden":false}]